CHANGES.txt
README.txt
setup.py
syntax-tryouts.txt
tests_to_implement.txt
yaxl.tailor
docs/developing-with-yaxl.txt
docs/index.txt
docs/style.css
yaxl/__init__.py
yaxl/xpathlib.py
yaxl/xpathparser.py
yaxl.egg-info/PKG-INFO
yaxl.egg-info/SOURCES.txt
yaxl.egg-info/dependency_links.txt
yaxl.egg-info/not-zip-safe
yaxl.egg-info/top_level.txt
yaxl/_unittests/ElementTestSuite.py
yaxl/_unittests/NamespaceTestSuite.py
yaxl/_unittests/ParserTestSuite.py
yaxl/_unittests/XPathTestSuite.py
yaxl/_unittests/__init__.py
yaxl/_unittests/testcases/doctests/20051006.txt
yaxl/_unittests/testcases/doctests/20051013.txt
yaxl/_unittests/testcases/xml/test_utf8_chinese_1.xml
yaxl/_unittests/testcases/xml/test_utf8_chinese_2.xml
