Metadata-Version: 1.0
Name: yaxl
Version: 0.0.17
Summary: Yet Another (Pythonic) XML Library
Home-page: http://www.ilowe.net/software/yaxl
Author: Iain Lowe
Author-email: yaxl@ilowe.net
License: MIT License
Keywords: xml xpath
Platform: UNKNOWN
Classifier: Development Status :: 4 - Beta
Classifier: Intended Audience :: Developers
Classifier: License :: OSI Approved :: MIT License
Classifier: Natural Language :: English
Classifier: Operating System :: OS Independent
Classifier: Programming Language :: Python
Classifier: Topic :: Software Development :: Libraries :: Python Modules
Classifier: Topic :: Text Processing :: Markup :: XML
